{
  "main": {
    "id": "8b86b8d3325bd985",
    "type": "split",
    "children": [
      {
        "id": "2ed4b40875d94d43",
        "type": "tabs",
        "children": [
          {
            "id": "7d7d814dd3dac3a1",
            "type": "leaf",
            "state": {
              "type": "markdown",
              "state": {
                "file": "project1.md",
                "mode": "source",
                "source": false
              },
              "icon": "lucide-file",
              "title": "project1"
            }
          }
        ]
      }
    ],
    "direction": "vertical"
  },
  "left": {
    "id": "ff0eb6cdf5e61360",
    "type": "split",
    "children": [
      {
        "id": "4ec1a690eb544dc4",
        "type": "tabs",
        "children": [
          {
            "id": "5efdcdb6e397ea9c",
            "type": "leaf",
            "state": {
              "type": "file-explorer",
              "state": {
                "sortOrder": "alphabetical",
                "autoReveal": false
              },
              "icon": "lucide-folder-closed",
              "title": "文件列表"
            }
          },
          {
            "id": "5a5a388c16726b75",
            "type": "leaf",
            "state": {
              "type": "search",
              "state": {
                "query": "",
                "matchingCase": false,
                "explainSearch": false,
                "collapseAll": false,
                "extraContext": false,
                "sortOrder": "alphabetical"
              },
              "icon": "lucide-search",
              "title": "搜索"
            }
          },
          {
            "id": "638622c217766557",
            "type": "leaf",
            "state": {
              "type": "bookmarks",
              "state": {},
              "icon": "lucide-bookmark",
              "title": "书签"
            }
          }
        ]
      }
    ],
    "direction": "horizontal",
    "width": 300
  },
  "right": {
    "id": "7a978cb9c219859e",
    "type": "split",
    "children": [
      {
        "id": "2380acefe448b03e",
        "type": "tabs",
        "children": [
          {
            "id": "ea0efdee3b6d4f05",
            "type": "leaf",
            "state": {
              "type": "backlink",
              "state": {
                "file": "project1.md",
                "collapseAll": false,
                "extraContext": false,
                "sortOrder": "alphabetical",
                "showSearch": false,
                "searchQuery": "",
                "backlinkCollapsed": false,
                "unlinkedCollapsed": true
              },
              "icon": "links-coming-in",
              "title": "project1 的反向链接列表"
            }
          },
          {
            "id": "d4177858b83e8967",
            "type": "leaf",
            "state": {
              "type": "outgoing-link",
              "state": {
                "file": "project1.md",
                "linksCollapsed": false,
                "unlinkedCollapsed": true
              },
              "icon": "links-going-out",
              "title": "project1 的出链列表"
            }
          },
          {
            "id": "5fa61f1562c9e857",
            "type": "leaf",
            "state": {
              "type": "tag",
              "state": {
                "sortOrder": "frequency",
                "useHierarchy": true,
                "showSearch": false,
                "searchQuery": ""
              },
              "icon": "lucide-tags",
              "title": "标签"
            }
          },
          {
            "id": "e5c29d401b668e3c",
            "type": "leaf",
            "state": {
              "type": "outline",
              "state": {
                "file": "project1.md",
                "followCursor": false,
                "showSearch": false,
                "searchQuery": ""
              },
              "icon": "lucide-list",
              "title": "project1 的大纲"
            }
          }
        ]
      }
    ],
    "direction": "horizontal",
    "width": 300,
    "collapsed": true
  },
  "left-ribbon": {
    "hiddenItems": {
      "switcher:打开快速切换": false,
      "graph:查看关系图谱": false,
      "canvas:新建白板": false,
      "daily-notes:打开/创建今天的日记": false,
      "templates:插入模板": false,
      "command-palette:打开命令面板": false
    }
  },
  "active": "7d7d814dd3dac3a1",
  "lastOpenFiles": [
    "project1_2.pdf",
    "E-R.png",
    "E-R-datagrip.png",
    "project1.md",
    "mysql.png",
    "database-diagram 2.png",
    "database-diagram.png"
  ]
}